wasm_cli_runner/__init__.py
wasm_cli_runner/__main__.py
wasm_cli_runner/VERSION
wasm_cli_runner/version.py
wasm_cli_runner/wasm_cli_runner.py
wasm_cli_runner-1.0.0.dist-info/LICENSE
wasm_cli_runner-1.0.0.dist-info/WHEEL
wasm_cli_runner-1.0.0.dist-info/METADATA
wasm_cli_runner-1.0.0.dist-info/RECORD
