Metadata-Version: 2.1
Name: wasm-cli-runner
Version: 1.0.0
Summary: Run WebAssembly Binary and Text files in the command line.
Author: miile7
Requires-Python: >=3.8,<4.0
Classifier: Programming Language :: Python :: 3
Classifier: Programming Language :: Python :: 3.8
Classifier: Programming Language :: Python :: 3.9
Classifier: Programming Language :: Python :: 3.10
Classifier: Programming Language :: Python :: 3.11
Requires-Dist: wasmtime (>=3.0.0,<4.0.0)
